folderstats/__init__.py
folderstats/__main__.py
folderstats-0.4.1.dist-info/LICENSE
folderstats-0.4.1.dist-info/METADATA
folderstats-0.4.1.dist-info/WHEEL
folderstats-0.4.1.dist-info/entry_points.txt
folderstats-0.4.1.dist-info/top_level.txt
folderstats-0.4.1.dist-info/RECORD
